[
  {
    "id": 1,
    "name": "عبدالله بن معجب",
    "job": "",
    "image": "abdullah.jpg",
    "description": "هنا وصف الشخص",
    "children": [2, 3, 4, 5, 6]
  },
  {
    "id": 2,
    "name": "محمد بن عبدالله",
    "job": "وزارة الكهرباء والماء",
    "image": "mohammadalajmi.jpg",
    "birth": "1982",
    "description": "هنا وصف الشخص",
    "children": [7, 8]
  },
  {
    "id": 3,
    "name": "فهيد بن عبدالله",
    "job": "وزارة الدفاع (متقاعد)",
    "image": "fhaidalajmi.jpg",
    "description": "هنا وصف الشخص",
    "children": [9, 10, 11]
  },
  {
    "id": 4,
    "name": "حطاب بن عبدالله",
    "job": "",
    "image": "fahad.jpg",
    "description": "هنا وصف الشخص",
    "children": [12, 13]
  },
  {
    "id": 5,
    "name": "سعد بن عبدالله",
    "job": "",
    "image": "turki.jpg",
    "description": "هنا وصف الشخص",
    "children": [14, 15]
  },
  {
    "id": 6,
    "name": "معجب بن عبدالله",
    "job": "",
    "image": "rayan.jpg",
    "description": "هنا وصف الشخص",
    "children": [16, 17, 18]
  },
  {
    "id": 7,
    "name": "عبدالله بن محمد",
    "birth": "2012",
    "image": "saif.jpg",
    "children": []
  },
   {
    "id": 8,
    "name": "صالح بن محمد",
    "image": "mohammed.jpg",
    "children": []
  },
  {
    "id": 9,
    "name": "مانع بن فهيد",
    "image": "saud.jpg",
    "children": []
  },
  {
    "id": 10,
    "name": "ماجد بن فهيد",
    "image": "fahad.jpg",
    "children": []
  },
  {
    "id": 11,
    "name": "محمد بن فهيد",
    "image": "turki.jpg",
    "children": []
  },
  {
    "id": 12,
    "name": "عبدالله بن حطاب",
    "birth": "2006",
    "image": "abdullahhattab.jpg",
    "children": []
  },
  {
    "id": 13,
    "name": "سعد بن حطاب",
    "birth": "2012",
    "image": "saadhattab.jpg",
    "children": []
  },
   {
    "id": 14,
    "name": "عبدالله بن سعد",
    "birth": "2005",
    "image": "abdullahsaad.jpg",
    "children": []
  },
  {
    "id": 15,
    "name": "حمد بن سعد",
    "birth": "2011",
    "image": "hamadsaad.jpg",
    "children": []
  },
  {
    "id": 16,
    "name": "عبدالله بن معجب",
    "image": "fahad.jpg",
    "children": [2]
  },
  {
    "id": 17,
    "name": "مانع بن معجب",
    "image": "turki.jpg",
    "children": [2]
  },
  {
    "id": 18,
    "name": "سعد بن معجب",
    "image": "rayan.jpg",
    "children": [3]
  }
]
